hatch_showcase/__init__.py
hatch_showcase/__main__.py
hatch_showcase/_version.py
hatch_showcase/fib.py
hatch_showcase/cli/__init__.py
hatch_showcase-0.5.0.dist-info/METADATA
hatch_showcase-0.5.0.dist-info/WHEEL
hatch_showcase-0.5.0.dist-info/entry_points.txt
hatch_showcase-0.5.0.dist-info/licenses/LICENSE.txt
hatch_showcase-0.5.0.dist-info/RECORD
