Metadata-Version: 2.1
Name: hatch-showcase
Version: 0.5.0
Summary: A project showcasing features and plugins for Hatch
Project-URL: Donate, https://github.com/sponsors/ofek
Project-URL: History, https://github.com/ofek/hatch-showcase/blob/master/HISTORY.md
Project-URL: Issues, https://github.com/ofek/hatch-showcase/issues
Project-URL: Source, https://github.com/ofek/hatch-showcase
Author-email: Ofek Lev <oss@ofek.dev>
License: MIT
License-File: LICENSE.txt
Keywords: hatch
Classifier: Development Status :: 4 - Beta
Classifier: License :: OSI Approved :: MIT License
Classifier: Programming Language :: Python
Classifier: Programming Language :: Python :: 3.7
Classifier: Programming Language :: Python :: 3.8
Classifier: Programming Language :: Python :: 3.9
Classifier: Programming Language :: Python :: 3.10
Classifier: Programming Language :: Python :: 3.11
Classifier: Programming Language :: Python :: Implementation :: CPython
Classifier: Programming Language :: Python :: Implementation :: PyPy
Requires-Python: >=3.7
Requires-Dist: click>=8.0.3
